PARSEbp/__init__.py
PARSEbp/cli.py
PARSEbp/core.py
PARSEbp/bin/MC-Annotate
PARSEbp/bin/USalign
parsebp-0.1.0.dist-info/licenses/LICENSE
parsebp-0.1.0.dist-info/METADATA
parsebp-0.1.0.dist-info/WHEEL
parsebp-0.1.0.dist-info/entry_points.txt
parsebp-0.1.0.dist-info/top_level.txt
parsebp-0.1.0.dist-info/RECORD
