Metadata-Version: 2.4
Name: PARSEbp
Version: 0.1.0
Summary: Pairwise Agreement-based RNA Scoring with Emphasis on Base Pairings
Home-page: https://github.com/Bhattacharya-Lab/PARSEbp
Author: Sumit Tarafder and Debswapna Bhattacharya
License: MIT
Classifier: Programming Language :: Python :: 3
Classifier: License :: OSI Approved :: MIT License
Classifier: Operating System :: POSIX :: Linux
Requires-Python: >=3.7
License-File: LICENSE
Requires-Dist: numpy
Requires-Dist: tqdm
Dynamic: author
Dynamic: classifier
Dynamic: description
Dynamic: description-content-type
Dynamic: home-page
Dynamic: license
Dynamic: license-file
Dynamic: requires-dist
Dynamic: requires-python
Dynamic: summary
